glu/__init__.py
glu/ai.py
glu/config.py
glu/gh.py
glu/jira.py
glu/local.py
glu/models.py
glu/utils.py
glu/cli/__init__.py
glu/cli/init.py
glu/cli/main.py
glu/cli/commit/__init__.py
glu/cli/commit/count.py
glu/cli/commit/index.py
glu/cli/commit/list.py
glu/cli/pr/__init__.py
glu/cli/pr/create.py
glu/cli/pr/index.py
glu/cli/pr/list.py
glu/cli/pr/merge.py
glu/cli/pr/open.py
glu/cli/pr/update.py
glu/cli/pr/view.py
glu/cli/ticket/__init__.py
glu/cli/ticket/create.py
glu/cli/ticket/index.py
glu/cli/ticket/list.py
glu/cli/ticket/open.py
glu/cli/ticket/view.py
glu/data/conventional_commit_types.json
glu/data/pull_request_template.md
glu_cli-2.7.4.dist-info/METADATA
glu_cli-2.7.4.dist-info/WHEEL
glu_cli-2.7.4.dist-info/entry_points.txt
glu_cli-2.7.4.dist-info/RECORD
