Metadata-Version: 2.4
Name: glu-cli
Version: 2.7.4
Summary: A CLI tool to facilitate the developer workflow
Requires-Python: >=3.10
Requires-Dist: gitpython>=3.1.44
Requires-Dist: glean-api-client>=0.5.1
Requires-Dist: httpx>=0.28.1
Requires-Dist: inquirerpy>=0.3.4
Requires-Dist: jira>=3.10.5
Requires-Dist: langchain-anthropic>=0.3.14
Requires-Dist: langchain-glean>=0.3.1
Requires-Dist: langchain-google-genai>=2.1.5
Requires-Dist: langchain-ollama>=0.3.3
Requires-Dist: langchain-openai>=0.3.18
Requires-Dist: langchain-xai>=0.2.4
Requires-Dist: pydantic>=2.11.5
Requires-Dist: pygithub>=2.6.1
Requires-Dist: python-dotenv>=1.1.0
Requires-Dist: thefuzz>=0.22.1
Requires-Dist: tiktoken>=0.9.0
Requires-Dist: toml>=0.10.2
Requires-Dist: typer>=0.15.4
